aiida_raspa/__init__.py
aiida_raspa/calculations/__init__.py
aiida_raspa/parsers/__init__.py
aiida_raspa/utils/__init__.py
aiida_raspa/utils/base_input_generator.py
aiida_raspa/utils/base_parser.py
aiida_raspa/utils/inspection_tools.py
aiida_raspa/workchains/__init__.py
aiida_raspa/workchains/base.py
aiida_raspa-2.0.0.dist-info/entry_points.txt
aiida_raspa-2.0.0.dist-info/LICENSE
aiida_raspa-2.0.0.dist-info/WHEEL
aiida_raspa-2.0.0.dist-info/METADATA
aiida_raspa-2.0.0.dist-info/RECORD
