Metadata-Version: 2.1
Name: aiida-raspa
Version: 2.0.0
Summary: AiiDA plugin for RASPA code
Keywords: aiida,workflows
Author-email: Aliaksandr Yakutovich <aliaksandr.yakutovich@epfl.ch>, Miriam Pougin <miriam.pougin@epfl.ch>
Requires-Python: >=3.8
Classifier: Development Status :: 5 - Production/Stable
Classifier: Framework :: AiiDA
Classifier: License :: OSI Approved :: MIT License
Classifier: Programming Language :: Python
Classifier: Programming Language :: Python :: 3.8
Classifier: Programming Language :: Python :: 3.9
Classifier: Programming Language :: Python :: 3.10
Classifier: Programming Language :: Python :: 3.11
Requires-Dist: aiida_core[atomic_tools]~=2.3
Requires-Dist: importlib_resources
Requires-Dist: sphinx ; extra == "docs"
Requires-Dist: sphinx-rtd-theme ; extra == "docs"
Requires-Dist: sphinxcontrib-contentui ; extra == "docs"
Requires-Dist: sphinxcontrib-details-directive ; extra == "docs"
Requires-Dist: pre-commit~=3.3 ; extra == "pre-commit"
Requires-Dist: black~=23.7 ; extra == "pre-commit"
Requires-Dist: isort~=5.12.0 ; extra == "pre-commit"
Requires-Dist: pylint~=2.17.0 ; extra == "pre-commit"
Requires-Dist: pgtest~=1.3 ; extra == "tests"
Requires-Dist: pytest~=6.0 ; extra == "tests"
Project-URL: Home, https://github.com/yakutovicha/aiida-raspa
Project-URL: Source, https://github.com/yakutovicha/aiida-raspa
Provides-Extra: docs
Provides-Extra: pre-commit
Provides-Extra: tests
